rosetta_finder/__init__.py
rosetta_finder/rosetta.py
rosetta_finder/rosetta_finder.py
rosetta_finder/app/__init__.py
rosetta_finder/app/cart_ddg.py
rosetta_finder/app/fastrelax.py
rosetta_finder/app/mutate_relax.py
rosetta_finder/app/pross.py
rosetta_finder/app/rosettaligand.py
rosetta_finder/app/supercharge.py
rosetta_finder/app/deps/cart_ddg/flags/cart2.script
rosetta_finder/app/deps/cart_ddg/flags/ddG.options
rosetta_finder/app/deps/cart_ddg/flags/ddG_relax.flag
rosetta_finder/app/deps/cart_ddg/flags/flags
rosetta_finder/app/deps/fastrelax/flags/fastrelax.example.flag
rosetta_finder/app/deps/mutate_relax/flags/cluster_scoring.flags
rosetta_finder/app/deps/mutate_relax/flags/generate_all_mutmover.awk
rosetta_finder/app/deps/mutate_relax/flags/generate_all_mutprotocol.awk
rosetta_finder/app/deps/mutate_relax/flags/generate_all_muttask.awk
rosetta_finder/app/deps/mutate_relax/xml/mutant_validation_temp.xml
rosetta_finder/app/deps/pross/flags/flags_nodelay
rosetta_finder/app/deps/pross/xmls/design_new.xml
rosetta_finder/app/deps/pross/xmls/filterscan_parallel.xml
rosetta_finder/app/deps/pross/xmls/refine.xml
rosetta_finder/app/deps/rosettaligand/flags/rosetta_ligand.flags
rosetta_finder/app/deps/rosettaligand/xmls/rosetta_ligand.xml
rosetta_finder/app/utils/CA_constraints.py
rosetta_finder/app/utils/__init__.py
rosetta_finder/app/utils/smiles2param.py
rosetta_finder/common/__init__.py
rosetta_finder/common/mutation.py
rosetta_finder/utils/__init__.py
rosetta_finder-0.1.0.dist-info/entry_points.txt
rosetta_finder-0.1.0.dist-info/LICENSE
rosetta_finder-0.1.0.dist-info/WHEEL
rosetta_finder-0.1.0.dist-info/METADATA
rosetta_finder-0.1.0.dist-info/RECORD
