Metadata-Version: 2.1
Name: rosetta_finder
Version: 0.1.0
Summary: Searching for Rosetta Binaries.
Author-email: Yinying Yao <yaoyy.hi@gmail.com>
Requires-Python: >=3.8
Classifier: Development Status :: 3 - Alpha
Classifier: Intended Audience :: Developers
Classifier: License :: OSI Approved :: MIT License
Classifier: Programming Language :: Python :: 3 :: Only
Classifier: Programming Language :: Python :: 3.8
Classifier: Programming Language :: Python :: 3.9
Classifier: Programming Language :: Python :: 3.10
Classifier: Programming Language :: Python :: 3.11
Classifier: Programming Language :: Python :: 3.12
Requires-Dist: pyspark>=3.0.0 ; extra == "spark"
Requires-Dist: bandit[toml]==1.7.10 ; extra == "test"
Requires-Dist: black==24.8.0 ; extra == "test"
Requires-Dist: check-manifest==0.49 ; extra == "test"
Requires-Dist: flake8-bugbear==24.8.19 ; extra == "test"
Requires-Dist: flake8-docstrings ; extra == "test"
Requires-Dist: flake8-formatter_junit_xml ; extra == "test"
Requires-Dist: flake8 ; extra == "test"
Requires-Dist: flake8-pyproject ; extra == "test"
Requires-Dist: pre-commit==3.5.0 ; extra == "test"
Requires-Dist: pylint==3.2.7 ; extra == "test"
Requires-Dist: pylint_junit ; extra == "test"
Requires-Dist: pytest-cov==5.0.0 ; extra == "test"
Requires-Dist: pytest-mock<3.14.1 ; extra == "test"
Requires-Dist: pytest-runner ; extra == "test"
Requires-Dist: pytest==8.3.3 ; extra == "test"
Requires-Dist: pytest-order ; extra == "test"
Requires-Dist: pytest-github-actions-annotate-failures ; extra == "test"
Requires-Dist: shellcheck-py==0.10.0.1 ; extra == "test"
Requires-Dist: joblib ; extra == "wrapper"
Requires-Dist: absl-py ; extra == "wrapper"
Requires-Dist: pandas ; extra == "wrapper"
Requires-Dist: biopython ; extra == "wrapper"
Requires-Dist: rdkit ; extra == "wrapper"
Requires-Dist: numpy>=1.20.3,<2 ; extra == "wrapper"
Project-URL: Documentation, https://github.com/YaoYinYing/rosetta_finder/tree/main#readme
Project-URL: Source, https://github.com/YaoYinYing/rosetta_finder
Project-URL: Tracker, https://github.com/YaoYinYing/rosetta_finder/issues
Provides-Extra: spark
Provides-Extra: test
Provides-Extra: wrapper
